CHANGES.txt
LICENSE.txt
MANIFEST.in
README.rst
devel_requirements_py27.txt
requirements.test.txt
requirements.txt
setup.cfg
setup.py
FlowCytometryTools/__init__.py
FlowCytometryTools/_doc.py
FlowCytometryTools/_version.py
FlowCytometryTools/core/__init__.py
FlowCytometryTools/core/bases.py
FlowCytometryTools/core/common_doc.py
FlowCytometryTools/core/containers.py
FlowCytometryTools/core/docstring.py
FlowCytometryTools/core/gates.py
FlowCytometryTools/core/graph.py
FlowCytometryTools/core/transforms.py
FlowCytometryTools/core/utils.py
FlowCytometryTools/gui/__init__.py
FlowCytometryTools/gui/dialogs.py
FlowCytometryTools/gui/fc_widget.py
FlowCytometryTools/gui/webagg_backend/__init__.py
FlowCytometryTools/gui/webagg_backend/gui.py
FlowCytometryTools/gui/wx_backend/__init__.py
FlowCytometryTools/gui/wx_backend/gui.py
FlowCytometryTools/gui/wx_backend/wireframe.py
FlowCytometryTools/tests/__init__.py
FlowCytometryTools/tests/test_fcs_reader.py
FlowCytometryTools/tests/test_gates.py
FlowCytometryTools/tests/test_imports.py
FlowCytometryTools/tests/test_transforms.py
FlowCytometryTools/tests/data/FlowCytometers/HTS_BD_LSR-II/HTS_BD_LSR_II_Mixed_Specimen_001_D6_D06.fcs
FlowCytometryTools/tests/data/Plate01/CFP_Well_A4.fcs
FlowCytometryTools/tests/data/Plate01/CFP_Well_B4.fcs
FlowCytometryTools/tests/data/Plate01/RFP_Well_A3.fcs
FlowCytometryTools/tests/data/Plate01/RFP_Well_A6.fcs
FlowCytometryTools/tests/data/Plate01/RFP_Well_B3.fcs
FlowCytometryTools/tests/data/Plate01/YFP_Well_A7.fcs
FlowCytometryTools/tests/data/Plate01/YFP_Well_C7.fcs
FlowCytometryTools/tests/data/Plate02/Mixed_Well_H1.001.fcs
FlowCytometryTools/tests/data/Plate02/Mixed_Well_H12.001.fcs
FlowCytometryTools/tests/data/Plate02/Mixed_Well_H3.001.fcs
FlowCytometryTools/tests/data/Plate02/Mixed_Well_H7.001.fcs
numpy_reduced_flowcytometrytools.egg-info/PKG-INFO
numpy_reduced_flowcytometrytools.egg-info/SOURCES.txt
numpy_reduced_flowcytometrytools.egg-info/dependency_links.txt
numpy_reduced_flowcytometrytools.egg-info/requires.txt
numpy_reduced_flowcytometrytools.egg-info/top_level.txt